Workbook

Sheet Applications
A1: Cristian Arcidiacono — 2026–27 job market
A2: This version: 19 October 2026.
A4: Institution | B4: Position | C4: Location | D4: Track · letter set | E4: Application deadline | F4: Letters due | G4: Days until letters due | H4: Letters required | I4: How letters are submitted | J4: Portal / address / timing | K4: Referee 1 | L4: Referee 2 | M4: Referee 3 | N4: Referee 4 | O4: All referees | P4: Letter status - for Cristian
A5: St John's College, Oxford | B5: Career Development Research Fellowship in Economics (4 yrs from Oct 2027) | C5: Oxford, UK | D5: Fellowship · Macro / economics | E5: 46318 | F5: 46325 | G5: =IF(F5<>"",F5-TODAY(),IF(E5<>"",E5-TODAY(),"")) -> 11 | H5: Names only at submission; 2 reports requested by the college | I5: College requests reports directly | J5: Reports due 12:00 noon UK, Fri 30 Oct; application 1pm Fri 23 Oct | K5: Benigno | L5: Reis | O5: =_xlfn.TEXTJOIN(", ",TRUE(),K5:N5) -> Benigno, Reis | P5: Names only
A6: University of St. Gallen | B6: Assistant Professor (tenure track), Macroeconomics | C6: St. Gallen, CH | D6: Academic · Macro / economics | E6: 46326 | F6: 46326 | G6: =IF(F6<>"",F6-TODAY(),IF(E6<>"",E6-TODAY(),"")) -> 12 | H6: 2 | I6: University portal (facultyrecruiting.unisg.ch) | J6: Contact facultyposition@unisg.ch (Prof. Winfried Koeniger) | K6: Benigno | L6: Reis | O6: =_xlfn.TEXTJOIN(", ",TRUE(),K6:N6) -> Benigno, Reis | P6: Referee action needed
A7: OECD, Economics Department | B7: Junior Economists / Economists (2-yr, Paris) | C7: Paris, FR | D7: Policy | E7: 46327 | F7: 46327 | G7: =IF(F7<>"",F7-TODAY(),IF(E7<>"",E7-TODAY(),"")) -> 13 | H7: 3 | I7: EconJobMarket (ad 12569) + email | J7: econjobmarket.org/positions/12569; JMP/CV/cover letter to mathieu.miranda@oecd.org | K7: Benigno | L7: Reis | M7: Hofmann | O7: =_xlfn.TEXTJOIN(", ",TRUE(),K7:N7) -> Benigno, Reis, Hofmann | P7: On platform – check attached
A8: Northwestern Kellogg | B8: Assistant Professor of Finance | C8: Evanston, US | D8: Academic · Finance | E8: 46327 | F8: 46327 | G8: =IF(F8<>"",F8-TODAY(),IF(E8<>"",E8-TODAY(),"")) -> 13 | H8: 3 | I8: Kellogg faculty-recruiting portal | J8: facultyrecruiting.northwestern.edu/apply/MjYzMg | K8: Benigno | L8: Reis | M8: Chaudhary | O8: =_xlfn.TEXTJOIN(", ",TRUE(),K8:N8) -> Benigno, Reis, Chaudhary | P8: Referee action needed
A9: Texas A&M University | B9: Assistant Professor of International Macroeconomics | C9: College Station, US | D9: Academic · Macro / economics | E9: 46327 | F9: 46327 | G9: =IF(F9<>"",F9-TODAY(),IF(E9<>"",E9-TODAY(),"")) -> 13 | H9: Not stated – check ad | I9: AEA JOE | J9: JOE listing (Aug 2026) | K9: Benigno | L9: Reis | M9: Hofmann | O9: =_xlfn.TEXTJOIN(", ",TRUE(),K9:N9) -> Benigno, Reis, Hofmann | P9: On platform – check attached
A10: EPFL / Swiss Finance Institute | B10: Faculty positions in Finance (two posts, one ad) | C10: Lausanne, CH | D10: Academic · Finance | E10: 46327 | G10: =IF(F10<>"",F10-TODAY(),IF(E10<>"",E10-TODAY(),"")) -> 13 | H10: Names only (3–5) | I10: Names supplied; EPFL requests letters later | J10: epfl.ch/about/working/?p=9052 | K10: Benigno | L10: Reis | M10: Chaudhary | O10: =_xlfn.TEXTJOIN(", ",TRUE(),K10:N10) -> Benigno, Reis, Chaudhary | P10: Names only
A11: Universitat Autònoma de Barcelona (UFAE / BSE) | B11: Assistant and Associate Professor positions (any field) | C11: Bellaterra, ES | D11: Academic · Macro / economics | E11: 46327 | F11: 46327 | G11: =IF(F11<>"",F11-TODAY(),IF(E11<>"",E11-TODAY(),"")) -> 13 | H11: 3 | I11: EconJobMarket (ad 12666) | J11: Online interviews 9–11 Dec | K11: Benigno | L11: Reis | M11: Hofmann | O11: =_xlfn.TEXTJOIN(", ",TRUE(),K11:N11) -> Benigno, Reis, Hofmann | P11: On platform – check attached
A12: Imperial College Business School | B12: Assistant/Associate/Full Professor in Economics | C12: London, UK | D12: Academic · Macro / economics | E12: 46329 | F12: 46329 | G12: =IF(F12<>"",F12-TODAY(),IF(E12<>"",E12-TODAY(),"")) -> 15 | H12: 3 | I12: EconJobMarket (ad 12773) | J12: econjobmarket.org/positions/12773 | K12: Benigno | L12: Reis | M12: Hofmann | O12: =_xlfn.TEXTJOIN(", ",TRUE(),K12:N12) -> Benigno, Reis, Hofmann | P12: On platform – check attached
A13: Oxford Saïd Business School | B13: Tenure-track position in Financial Economics | C13: Oxford, UK | D13: Academic · Finance | E13: 46332 | G13: =IF(F13<>"",F13-TODAY(),IF(E13<>"",E13-TODAY(),"")) -> 18 | H13: None at this stage | I13: Expression-of-interest stage only | J13: careers.sbs.ox.ac.uk vacancy 1024 | K13: Benigno | L13: Reis | M13: Chaudhary | O13: =_xlfn.TEXTJOIN(", ",TRUE(),K13:N13) -> Benigno, Reis, Chaudhary | P13: Not needed yet
A14: MIT, Department of Economics | B14: Assistant Professor (any field) | C14: Cambridge MA, US | D14: Academic · Macro / economics | E14: 46332 | F14: 46332 | G14: =IF(F14<>"",F14-TODAY(),IF(E14<>"",E14-TODAY(),"")) -> 18 | H14: 3 | I14: MIT portal / EconJobMarket (ad 12621) | J14: Letters also due 6 Nov | K14: Benigno | L14: Reis | M14: Hofmann | O14: =_xlfn.TEXTJOIN(", ",TRUE(),K14:N14) -> Benigno, Reis, Hofmann | P14: On platform – check attached
A15: Stanford University, Department of Economics | B15: Assistant Professor (any field) | C15: Stanford, US | D15: Academic · Macro / economics | E15: 46332 | F15: 46332 | G15: =IF(F15<>"",F15-TODAY(),IF(E15<>"",E15-TODAY(),"")) -> 18 | H15: 3 | I15: EconJobMarket (ad 12662) | K15: Benigno | L15: Reis | M15: Hofmann | O15: =_xlfn.TEXTJOIN(", ",TRUE(),K15:N15) -> Benigno, Reis, Hofmann | P15: On platform – check attached
A16: Cornell University, Economics | B16: Assistant Professor (international) | C16: Ithaca, US | D16: Academic · Macro / economics | E16: 46333 | F16: 46333 | G16: =IF(F16<>"",F16-TODAY(),IF(E16<>"",E16-TODAY(),"")) -> 19 | H16: Not stated – check ad | I16: See JOE ad | K16: Benigno | L16: Reis | M16: Hofmann | O16: =_xlfn.TEXTJOIN(", ",TRUE(),K16:N16) -> Benigno, Reis, Hofmann | P16: On platform – check attached
A17: Yale University, Department of Economics | B17: Assistant Professor (any field) | C17: New Haven, US | D17: Academic · Macro / economics | E17: 46333 | F17: 46333 | G17: =IF(F17<>"",F17-TODAY(),IF(E17<>"",E17-TODAY(),"")) -> 19 | H17: 3 | I17: Interfolio 192292 | J17: JOE shows 31 Jan 2027, but the ad asks for applications before 7 Nov | K17: Benigno | L17: Reis | M17: Hofmann | O17: =_xlfn.TEXTJOIN(", ",TRUE(),K17:N17) -> Benigno, Reis, Hofmann | P17: On platform – check attached
A18: University of Michigan | B18: Assistant Professor (any field) | C18: Ann Arbor, US | D18: Academic · Macro / economics | E18: 46333 | F18: 46333 | G18: =IF(F18<>"",F18-TODAY(),IF(E18<>"",E18-TODAY(),"")) -> 19 | H18: 3 | I18: EconJobMarket (ad 12669) | J18: First consideration 7 Nov; final 31 Dec | K18: Benigno | L18: Reis | M18: Hofmann | O18: =_xlfn.TEXTJOIN(", ",TRUE(),K18:N18) -> Benigno, Reis, Hofmann | P18: On platform – check attached
A19: Federal Reserve Bank of New York | B19: Economist (PhD), Research & Statistics | C19: New York, US | D19: Policy | E19: 46327 | F19: 46334 | G19: =IF(F19<>"",F19-TODAY(),IF(E19<>"",E19-TODAY(),"")) -> 20 | H19: 3 | I19: NY Fed Workday portal | J19: Letters accepted up to one week after the application deadline | K19: Benigno | L19: Reis | M19: Hofmann | O19: =_xlfn.TEXTJOIN(", ",TRUE(),K19:N19) -> Benigno, Reis, Hofmann | P19: Referee action needed
A20: Bank for International Settlements (MED) | B20: Economist / Senior Economist / Principal Economist | C20: Basel, CH | D20: Policy | E20: 46334 | F20: 46334 | G20: =IF(F20<>"",F20-TODAY(),IF(E20<>"",E20-TODAY(),"")) -> 20 | H20: 3 | I20: AEA JOE only | J20: JOE listing 2026-02_111478115 – letters uploaded through JOE | K20: Benigno | L20: Reis | M20: Hofmann | O20: =_xlfn.TEXTJOIN(", ",TRUE(),K20:N20) -> Benigno, Reis, Hofmann | P20: On platform – check attached
A21: Toulouse School of Economics | B21: Assistant Professor (tenure track) | C21: Toulouse, FR | D21: Academic · Macro / economics | E21: 46334 | F21: 46334 | G21: =IF(F21<>"",F21-TODAY(),IF(E21<>"",E21-TODAY(),"")) -> 20 | H21: 3 | I21: EconJobMarket (ad 12736) | J21: econjobmarket.org/positions/12736 | K21: Benigno | L21: Reis | M21: Hofmann | O21: =_xlfn.TEXTJOIN(", ",TRUE(),K21:N21) -> Benigno, Reis, Hofmann | P21: On platform – check attached
A22: University of Konstanz | B22: Assistant Professor / Postdoc (economics) | C22: Konstanz, DE | D22: Academic · Macro / economics | E22: 46334 | F22: 46334 | G22: =IF(F22<>"",F22-TODAY(),IF(E22<>"",E22-TODAY(),"")) -> 20 | H22: 2 | I22: See ad | K22: Benigno | L22: Reis | O22: =_xlfn.TEXTJOIN(", ",TRUE(),K22:N22) -> Benigno, Reis | P22: Referee action needed
A23: Clare / Churchill / Fitzwilliam / Murray Edwards / Trinity Hall (Cambridge) | B23: Early Career Research Fellowships 2027 (joint scheme, 3 yrs) | C23: Cambridge, UK | D23: Fellowship · Macro / economics | E23: 46335 | F23: 46335 | G23: =IF(F23<>"",F23-TODAY(),IF(E23<>"",E23-TODAY(),"")) -> 21 | H23: Per further particulars (jrf.chu.cam.ac.uk/rf_2027) | I23: College online form | J23: clare.cam.ac.uk/JRF-Eligibility | K23: Benigno | L23: Reis | O23: =_xlfn.TEXTJOIN(", ",TRUE(),K23:N23) -> Benigno, Reis | P23: Referee action needed
A24: Harvard Business School – BGIE | B24: Assistant Professor, Business, Government & the International Economy | C24: Boston, US | D24: Academic · Macro / economics | E24: 46335 | F24: 46335 | G24: =IF(F24<>"",F24-TODAY(),IF(E24<>"",E24-TODAY(),"")) -> 21 | H24: Not stated – check ad | I24: Interfolio 192151 | J24: apply.interfolio.com/192151 | K24: Benigno | L24: Reis | M24: Hofmann | O24: =_xlfn.TEXTJOIN(", ",TRUE(),K24:N24) -> Benigno, Reis, Hofmann | P24: On platform – check attached
A25: INSEAD, Finance Area | B25: Assistant Professor of Finance | C25: Fontainebleau, FR | D25: Academic · Finance | E25: 46336 | F25: 46336 | G25: =IF(F25<>"",F25-TODAY(),IF(E25<>"",E25-TODAY(),"")) -> 22 | H25: 3 or more – uploaded by the candidate | I25: Interfolio 194812 – candidate uploads confidential letters | J25: apply.interfolio.com/194812 | K25: Benigno | L25: Reis | M25: Chaudhary | O25: =_xlfn.TEXTJOIN(", ",TRUE(),K25:N25) -> Benigno, Reis, Chaudhary | P25: On platform – check attached
A26: Stanford GSB, Economics | B26: Faculty positions in Economics | C26: Stanford, US | D26: Academic · Macro / economics | E26: 46336 | F26: 46336 | G26: =IF(F26<>"",F26-TODAY(),IF(E26<>"",E26-TODAY(),"")) -> 22 | H26: 3 | I26: AcademicJobsOnline | K26: Benigno | L26: Reis | M26: Hofmann | O26: =_xlfn.TEXTJOIN(", ",TRUE(),K26:N26) -> Benigno, Reis, Hofmann | P26: On platform – check attached
A27: Banca d'Italia | B27: Research Fellowships for young economists 2026 (4 posts; 12+12 months, from Nov 2027) | C27: Rome, IT | D27: Policy | E27: 46339 | F27: 46339 | G27: =IF(F27<>"",F27-TODAY(),IF(E27<>"",E27-TODAY(),"")) -> 25 | H27: At least 2 – SIGNED, sent by the referee | I27: Referee emails the letter directly to the Bank | J27: personale.fellowship@bancaditalia.it – deadline 12:00 CET, 13 Nov | K27: Benigno | L27: Reis | M27: Hofmann | O27: =_xlfn.TEXTJOIN(", ",TRUE(),K27:N27) -> Benigno, Reis, Hofmann | P27: Referee action needed
A28: EIEF (Einaudi Institute) | B28: Assistant Professor (2 posts) | C28: Rome, IT | D28: Academic · Macro / economics | E28: 46339 | F28: 46339 | G28: =IF(F28<>"",F28-TODAY(),IF(E28<>"",E28-TODAY(),"")) -> 25 | H28: 3 | I28: EconJobMarket (ad 12688) | J28: econjobmarket.org/positions/12688 | K28: Benigno | L28: Reis | M28: Hofmann | O28: =_xlfn.TEXTJOIN(", ",TRUE(),K28:N28) -> Benigno, Reis, Hofmann | P28: On platform – check attached
A29: IIES, Stockholm University | B29: Tenure-track Assistant Professor | C29: Stockholm, SE | D29: Academic · Macro / economics | E29: 46339 | F29: 46339 | G29: =IF(F29<>"",F29-TODAY(),IF(E29<>"",E29-TODAY(),"")) -> 25 | H29: 3 | I29: EconJobMarket (ad 12840) | J29: econjobmarket.org/positions/12840 | K29: Benigno | L29: Reis | M29: Hofmann | O29: =_xlfn.TEXTJOIN(", ",TRUE(),K29:N29) -> Benigno, Reis, Hofmann | P29: On platform – check attached
A30: UCL, Department of Economics | B30: Assistant Professor (Lecturer) in Economics | C30: London, UK | D30: Academic · Macro / economics | E30: 46339 | F30: 46339 | G30: =IF(F30<>"",F30-TODAY(),IF(E30<>"",E30-TODAY(),"")) -> 25 | H30: 3 | I30: EconJobMarket (ad 12850) | J30: econjobmarket.org/positions/12850 | K30: Benigno | L30: Reis | M30: Hofmann | O30: =_xlfn.TEXTJOIN(", ",TRUE(),K30:N30) -> Benigno, Reis, Hofmann | P30: On platform – check attached
A31: UCL, Economics / School of Management | B31: Assistant Professor (Lecturer) in Finance | C31: London, UK | D31: Academic · Finance | E31: 46339 | F31: 46339 | G31: =IF(F31<>"",F31-TODAY(),IF(E31<>"",E31-TODAY(),"")) -> 25 | H31: 3 | I31: EconJobMarket (ad 12826) | J31: econjobmarket.org/positions/12826 | K31: Benigno | L31: Reis | M31: Chaudhary | O31: =_xlfn.TEXTJOIN(", ",TRUE(),K31:N31) -> Benigno, Reis, Chaudhary | P31: On platform – check attached
A32: HEC Paris | B32: Assistant Professor of Finance | C32: Jouy-en-Josas, FR | D32: Academic · Finance | E32: 46339 | F32: 46339 | G32: =IF(F32<>"",F32-TODAY(),IF(E32<>"",E32-TODAY(),"")) -> 25 | H32: 3 | I32: EconJobMarket (ad 12819) | J32: econjobmarket.org/positions/12819 | K32: Benigno | L32: Reis | M32: Chaudhary | O32: =_xlfn.TEXTJOIN(", ",TRUE(),K32:N32) -> Benigno, Reis, Chaudhary | P32: On platform – check attached
A33: Columbia University, Economics | B33: Assistant Professor (junior) | C33: New York, US | D33: Academic · Macro / economics | E33: 46339 | F33: 46339 | G33: =IF(F33<>"",F33-TODAY(),IF(E33<>"",E33-TODAY(),"")) -> 25 | H33: 3 | I33: EconJobMarket (ad 12750) | J33: econjobmarket.org/positions/12750 | K33: Benigno | L33: Reis | M33: Hofmann | O33: =_xlfn.TEXTJOIN(", ",TRUE(),K33:N33) -> Benigno, Reis, Hofmann | P33: On platform – check attached
A34: LSE, Department of Finance | B34: Assistant Professor of Finance | C34: London, UK | D34: Academic · Finance | E34: 46339 | F34: 46339 | G34: =IF(F34<>"",F34-TODAY(),IF(E34<>"",E34-TODAY(),"")) -> 25 | H34: Not stated – check ad | I34: AEA JOE / LSE portal | K34: Benigno | L34: Reis | M34: Chaudhary | O34: =_xlfn.TEXTJOIN(", ",TRUE(),K34:N34) -> Benigno, Reis, Chaudhary | P34: On platform – check attached
A35: McGill, Desautels | B35: Tenure-track position in Finance | C35: Montréal, CA | D35: Academic · Finance | E35: 46339 | F35: 46339 | G35: =IF(F35<>"",F35-TODAY(),IF(E35<>"",E35-TODAY(),"")) -> 25 | H35: 3 | I35: McGill Workday | J35: Date unverified | K35: Benigno | L35: Reis | M35: Chaudhary | O35: =_xlfn.TEXTJOIN(", ",TRUE(),K35:N35) -> Benigno, Reis, Chaudhary | P35: Referee action needed
A36: Yale School of Management | B36: Assistant or Associate Professor of Economics | C36: New Haven, US | D36: Academic · Macro / economics | E36: 46339 | F36: 46339 | G36: =IF(F36<>"",F36-TODAY(),IF(E36<>"",E36-TODAY(),"")) -> 25 | H36: Not stated – check ad | I36: Interfolio 195222 | J36: apply.interfolio.com/195222 | K36: Benigno | L36: Reis | M36: Hofmann | O36: =_xlfn.TEXTJOIN(", ",TRUE(),K36:N36) -> Benigno, Reis, Hofmann | P36: On platform – check attached
A37: Universidad Carlos III de Madrid | B37: Assistant Professor of Economics | C37: Getafe, ES | D37: Academic · Macro / economics | E37: 46339 | F37: 46339 | G37: =IF(F37<>"",F37-TODAY(),IF(E37<>"",E37-TODAY(),"")) -> 25 | H37: 3 | I37: EconJobMarket (ad 12677) | J37: Online interviews 14–17 Dec | K37: Benigno | L37: Reis | M37: Hofmann | O37: =_xlfn.TEXTJOIN(", ",TRUE(),K37:N37) -> Benigno, Reis, Hofmann | P37: On platform – check attached
A38: University College London – Stone Centre | B38: Research Fellow (wealth inequality, macro) | C38: London, UK | D38: Fellowship · Macro / economics | E38: 46339 | F38: 46339 | G38: =IF(F38<>"",F38-TODAY(),IF(E38<>"",E38-TODAY(),"")) -> 25 | H38: 3 | I38: EconJobMarket (ad 12781) | K38: Benigno | L38: Reis | M38: Hofmann | O38: =_xlfn.TEXTJOIN(", ",TRUE(),K38:N38) -> Benigno, Reis, Hofmann | P38: On platform – check attached
A39: Bocconi University, Department of Finance | B39: Assistant Professor of Finance (tenure track) | C39: Milan, IT | D39: Academic · Finance | E39: 46341 | F39: 46341 | G39: =IF(F39<>"",F39-TODAY(),IF(E39<>"",E39-TODAY(),"")) -> 27 | H39: 3 | I39: Bocconi job-market portal | J39: jobmarket.unibocconi.eu/?id=1005 – 23:59 Italian time | K39: Benigno | L39: Reis | M39: Chaudhary | O39: =_xlfn.TEXTJOIN(", ",TRUE(),K39:N39) -> Benigno, Reis, Chaudhary | P39: Referee action needed
A40: Université de Montréal | B40: Assistant Professor of Macroeconomics | C40: Montréal, CA | D40: Academic · Macro / economics | E40: 46341 | F40: 46341 | G40: =IF(F40<>"",F40-TODAY(),IF(E40<>"",E40-TODAY(),"")) -> 27 | H40: 3 | I40: EconJobMarket (ad 12645) | J40: econjobmarket.org/positions/12645 | K40: Benigno | L40: Reis | M40: Hofmann | O40: =_xlfn.TEXTJOIN(", ",TRUE(),K40:N40) -> Benigno, Reis, Hofmann | P40: On platform – check attached
A41: Erasmus School of Economics | B41: Assistant Professor in Macroeconomics / International Economics (TT) | C41: Rotterdam, NL | D41: Academic · Macro / economics | E41: 46341 | F41: 46341 | G41: =IF(F41<>"",F41-TODAY(),IF(E41<>"",E41-TODAY(),"")) -> 27 | H41: 3 | I41: EconJobMarket (ad 12857) | J41: econjobmarket.org/positions/12857 | K41: Benigno | L41: Reis | M41: Hofmann | O41: =_xlfn.TEXTJOIN(", ",TRUE(),K41:N41) -> Benigno, Reis, Hofmann | P41: On platform – check attached
A42: University of Mannheim | B42: Assistant Professorships (W1) in Empirical / Quantitative Macroeconomics | C42: Mannheim, DE | D42: Academic · Macro / economics | E42: 46341 | F42: 46341 | G42: =IF(F42<>"",F42-TODAY(),IF(E42<>"",E42-TODAY(),"")) -> 27 | H42: Not stated in ad (EJM form: 3) | I42: EconJobMarket only (ad 12801) | J42: econjobmarket.org/positions/12801 | K42: Benigno | L42: Reis | M42: Hofmann | O42: =_xlfn.TEXTJOIN(", ",TRUE(),K42:N42) -> Benigno, Reis, Hofmann | P42: On platform – check attached
A43: Université de Genève – GFRI | B43: Assistant/Associate Professor (TT) in Finance, ref. 7008 | C43: Geneva, CH | D43: Academic · Finance | E43: 46341 | G43: =IF(F43<>"",F43-TODAY(),IF(E43<>"",E43-TODAY(),"")) -> 27 | H43: None now ('not requested for now') | I43: — | K43: Benigno | L43: Reis | M43: Chaudhary | O43: =_xlfn.TEXTJOIN(", ",TRUE(),K43:N43) -> Benigno, Reis, Chaudhary | P43: Not needed yet
A44: Danmarks Nationalbank | B44: Economist / Senior Economist / Adviser (international macro-finance: FX, capital flows) | C44: Copenhagen, DK | D44: Policy | E44: 46341 | F44: 46341 | G44: =IF(F44<>"",F44-TODAY(),IF(E44<>"",E44-TODAY(),"")) -> 27 | H44: 3 | I44: EconJobMarket (ad 12834) | J44: Interviews in the EEA job-market window, 14–17 Dec | K44: Benigno | L44: Reis | M44: Hofmann | O44: =_xlfn.TEXTJOIN(", ",TRUE(),K44:N44) -> Benigno, Reis, Hofmann | P44: On platform – check attached
A45: IE University – School of Politics, Economics & Global Affairs | B45: Tenure-track Faculty in Economics (macro, monetary, time-series econometrics) | C45: Madrid, ES | D45: Academic · Macro / economics | E45: 46341 | F45: 46341 | G45: =IF(F45<>"",F45-TODAY(),IF(E45<>"",E45-TODAY(),"")) -> 27 | H45: 3 | I45: EconJobMarket (ad 12742) | K45: Benigno | L45: Reis | M45: Hofmann | O45: =_xlfn.TEXTJOIN(", ",TRUE(),K45:N45) -> Benigno, Reis, Hofmann | P45: On platform – check attached
A46: Université de Genève – GSEM | B46: Tenure-track Assistant Professor in Economics | C46: Geneva, CH | D46: Academic · Macro / economics | E46: 46341 | G46: =IF(F46<>"",F46-TODAY(),IF(E46<>"",E46-TODAY(),"")) -> 27 | H46: Names only (list of 3) | I46: EconJobMarket (ad 12769) | J46: Full consideration 15 Nov; final 31 Jan 2027 | K46: Benigno | L46: Reis | M46: Hofmann | O46: =_xlfn.TEXTJOIN(", ",TRUE(),K46:N46) -> Benigno, Reis, Hofmann | P46: Names only
A47: IE University | B47: Tenure-track Assistant Professor of Finance | C47: Madrid, ES | D47: Academic · Finance | E47: 46341 | F47: 46341 | G47: =IF(F47<>"",F47-TODAY(),IF(E47<>"",E47-TODAY(),"")) -> 27 | H47: 3 | I47: EconJobMarket (ad 12674) | K47: Benigno | L47: Reis | M47: Chaudhary | O47: =_xlfn.TEXTJOIN(", ",TRUE(),K47:N47) -> Benigno, Reis, Chaudhary | P47: On platform – check attached
A48: CUNEF Universidad | B48: Assistant Professor (Economics / Finance) | C48: Madrid, ES | D48: Academic · Macro / economics | E48: 46341 | F48: 46341 | G48: =IF(F48<>"",F48-TODAY(),IF(E48<>"",E48-TODAY(),"")) -> 27 | H48: 3 | I48: EconJobMarket (ad 12691) | K48: Benigno | L48: Reis | M48: Hofmann | O48: =_xlfn.TEXTJOIN(", ",TRUE(),K48:N48) -> Benigno, Reis, Hofmann | P48: On platform – check attached
A49: University of Zurich, Finance | B49: Assistant Professorship in Finance (TT) | C49: Zurich, CH | D49: Academic · Finance | E49: 46341 | G49: =IF(F49<>"",F49-TODAY(),IF(E49<>"",E49-TODAY(),"")) -> 27 | H49: Names only | I49: jobs.uzh.ch | K49: Benigno | L49: Reis | M49: Chaudhary | O49: =_xlfn.TEXTJOIN(", ",TRUE(),K49:N49) -> Benigno, Reis, Chaudhary | P49: Names only
A50: University of Bonn | B50: Postdoctoral positions in Macroeconomics (2) | C50: Bonn, DE | D50: Academic · Macro / economics | E50: 46341 | F50: 46341 | G50: =IF(F50<>"",F50-TODAY(),IF(E50<>"",E50-TODAY(),"")) -> 27 | H50: 2 | I50: EconJobMarket | K50: Benigno | L50: Reis | O50: =_xlfn.TEXTJOIN(", ",TRUE(),K50:N50) -> Benigno, Reis | P50: On platform – check attached
A51: SOFI, Stockholm University | B51: Assistant Professor (labour) | C51: Stockholm, SE | D51: Academic · Macro / economics | E51: 46341 | F51: 46341 | G51: =IF(F51<>"",F51-TODAY(),IF(E51<>"",E51-TODAY(),"")) -> 27 | H51: 3 | I51: EconJobMarket | K51: Benigno | L51: Reis | M51: Hofmann | O51: =_xlfn.TEXTJOIN(", ",TRUE(),K51:N51) -> Benigno, Reis, Hofmann | P51: On platform – check attached
A52: Institute for Fiscal Studies | B52: Research Economist – Postdoctoral / Postdoctoral Fellow | C52: London, UK | D52: Research institute · Macro / economics | E52: 46341 | F52: 46341 | G52: =IF(F52<>"",F52-TODAY(),IF(E52<>"",E52-TODAY(),"")) -> 27 | H52: 3 | I52: EconJobMarket (ads 12705 / 12665) | K52: Benigno | L52: Reis | M52: Hofmann | O52: =_xlfn.TEXTJOIN(", ",TRUE(),K52:N52) -> Benigno, Reis, Hofmann | P52: On platform – check attached
A53: Williams College | B53: Assistant Professor of Economics | C53: Williamstown, US | D53: Academic · Macro / economics | E53: 46341 | F53: 46341 | G53: =IF(F53<>"",F53-TODAY(),IF(E53<>"",E53-TODAY(),"")) -> 27 | H53: 3 | I53: Interfolio 190595 | K53: Benigno | L53: Reis | M53: Hofmann | O53: =_xlfn.TEXTJOIN(", ",TRUE(),K53:N53) -> Benigno, Reis, Hofmann | P53: On platform – check attached
A54: MIT Sloan | B54: Assistant Professor (Finance / Economics) | C54: Cambridge MA, US | D54: Academic · Finance | E54: 46341 | F54: 46341 | G54: =IF(F54<>"",F54-TODAY(),IF(E54<>"",E54-TODAY(),"")) -> 27 | H54: 3 | I54: See ad | K54: Benigno | L54: Reis | M54: Chaudhary | O54: =_xlfn.TEXTJOIN(", ",TRUE(),K54:N54) -> Benigno, Reis, Chaudhary | P54: Referee action needed
A55: University of Notre Dame | B55: Assistant Professor (macro priority) | C55: Notre Dame, US | D55: Academic · Macro / economics | E55: 46341 | F55: 46341 | G55: =IF(F55<>"",F55-TODAY(),IF(E55<>"",E55-TODAY(),"")) -> 27 | H55: Not stated – check ad | I55: Interfolio 188748 | J55: Priority date 15 Nov | K55: Benigno | L55: Reis | M55: Hofmann | O55: =_xlfn.TEXTJOIN(", ",TRUE(),K55:N55) -> Benigno, Reis, Hofmann | P55: On platform – check attached
A56: Federal Reserve Bank of Dallas | B56: Economists / Senior Economists (macro, monetary, international, finance) | C56: Dallas, US | D56: Policy | E56: 46341 | F56: 46341 | G56: =IF(F56<>"",F56-TODAY(),IF(E56<>"",E56-TODAY(),"")) -> 27 | H56: 3 | I56: EconJobMarket (ad 12793) | J56: econjobmarket.org/positions/12793 – letters must be RECEIVED by the deadline | K56: Benigno | L56: Reis | M56: Hofmann | O56: =_xlfn.TEXTJOIN(", ",TRUE(),K56:N56) -> Benigno, Reis, Hofmann | P56: On platform – check attached
A57: Inter-American Development Bank, Research Dept | B57: Research Economists | C57: Washington DC, US | D57: Policy | E57: 46341 | F57: 46341 | G57: =IF(F57<>"",F57-TODAY(),IF(E57<>"",E57-TODAY(),"")) -> 27 | H57: 3 | I57: AEA JOE (letters) + IDB careers site | J57: JOE listing 2026-02_111478277 | K57: Benigno | L57: Reis | M57: Hofmann | O57: =_xlfn.TEXTJOIN(", ",TRUE(),K57:N57) -> Benigno, Reis, Hofmann | P57: On platform – check attached
A58: Imperial College Business School | B58: Assistant/Associate/Full Professor in Finance | C58: London, UK | D58: Academic · Finance | E58: 46341 | F58: 46341 | G58: =IF(F58<>"",F58-TODAY(),IF(E58<>"",E58-TODAY(),"")) -> 27 | H58: Not stated – check ad | I58: AEA JOE | K58: Benigno | L58: Reis | M58: Chaudhary | O58: =_xlfn.TEXTJOIN(", ",TRUE(),K58:N58) -> Benigno, Reis, Chaudhary | P58: On platform – check attached
A59: Tilburg University | B59: Assistant Professor in Economics (open field) | C59: Tilburg, NL | D59: Academic · Macro / economics | E59: 46341 | F59: 46341 | G59: =IF(F59<>"",F59-TODAY(),IF(E59<>"",E59-TODAY(),"")) -> 27 | H59: 3 | I59: EconJobMarket (ad 12825) | J59: EEA job-market participant | K59: Benigno | L59: Reis | M59: Hofmann | O59: =_xlfn.TEXTJOIN(", ",TRUE(),K59:N59) -> Benigno, Reis, Hofmann | P59: On platform – check attached
A60: Utrecht University School of Economics | B60: Assistant Professor in Economics (public economics) | C60: Utrecht, NL | D60: Academic · Macro / economics | E60: 46341 | F60: 46341 | G60: =IF(F60<>"",F60-TODAY(),IF(E60<>"",E60-TODAY(),"")) -> 27 | H60: 2–3 | I60: EconJobMarket (ad 12817) | K60: Benigno | L60: Reis | O60: =_xlfn.TEXTJOIN(", ",TRUE(),K60:N60) -> Benigno, Reis | P60: On platform – check attached
A61: Católica Lisbon SBE | B61: Assistant Professor (TT) in Finance | C61: Lisbon, PT | D61: Academic · Finance | E61: 46341 | F61: 46341 | G61: =IF(F61<>"",F61-TODAY(),IF(E61<>"",E61-TODAY(),"")) -> 27 | H61: 3 | I61: EconJobMarket (ad 12663) | J61: Target date 8 Nov | K61: Benigno | L61: Reis | M61: Chaudhary | O61: =_xlfn.TEXTJOIN(", ",TRUE(),K61:N61) -> Benigno, Reis, Chaudhary | P61: On platform – check attached
A62: Federal Reserve Bank of Cleveland | B62: Economist / Senior Economist | C62: Cleveland, US | D62: Policy | E62: 46362 | F62: 46341 | G62: =IF(F62<>"",F62-TODAY(),IF(E62<>"",E62-TODAY(),"")) -> 27 | H62: 3 | I62: EconJobMarket (ad 12654) | J62: Full consideration 15 Nov; final 6 Dec | K62: Benigno | L62: Reis | M62: Hofmann | O62: =_xlfn.TEXTJOIN(", ",TRUE(),K62:N62) -> Benigno, Reis, Hofmann | P62: On platform – check attached
A63: DePaul University | B63: Assistant Professor of Economics (international macro, macro-finance) | C63: Chicago, US | D63: Academic · Macro / economics | E63: 46341 | F63: 46341 | G63: =IF(F63<>"",F63-TODAY(),IF(E63<>"",E63-TODAY(),"")) -> 27 | H63: 3 | I63: Interfolio 188852 | J63: Preference before 15 Nov; final 31 Jan 2027 | K63: Benigno | L63: Reis | M63: Hofmann | O63: =_xlfn.TEXTJOIN(", ",TRUE(),K63:N63) -> Benigno, Reis, Hofmann | P63: On platform – check attached
A64: University of Georgia – Terry College | B64: Assistant/Associate Professor, Macroeconomics | C64: Athens GA, US | D64: Academic · Macro / economics | E64: 46341 | F64: 46341 | G64: =IF(F64<>"",F64-TODAY(),IF(E64<>"",E64-TODAY(),"")) -> 27 | H64: 3 | I64: UGA portal + AEA JOE | J64: Full consideration 15 Nov; final 31 Jan 2027 | K64: Benigno | L64: Reis | M64: Hofmann | O64: =_xlfn.TEXTJOIN(", ",TRUE(),K64:N64) -> Benigno, Reis, Hofmann | P64: On platform – check attached
A65: Bocconi University, Economics (call 987) | B65: Assistant Professor of Economics (junior) – CONDITIONAL | C65: Milan, IT | D65: Academic · Macro / economics | E65: 46341 | F65: 46341 | G65: =IF(F65<>"",F65-TODAY(),IF(E65<>"",E65-TODAY(),"")) -> 27 | H65: 3 | I65: Bocconi job-market portal | J65: jobmarket.unibocconi.eu/?id=987 | K65: Benigno | L65: Reis | M65: Hofmann | O65: =_xlfn.TEXTJOIN(", ",TRUE(),K65:N65) -> Benigno, Reis, Hofmann | P65: Referee action needed
A66: Maastricht University | B66: Assistant Professor, Macroeconomics – CONDITIONAL | C66: Maastricht, NL | D66: Academic · Macro / economics | E66: 46341 | G66: =IF(F66<>"",F66-TODAY(),IF(E66<>"",E66-TODAY(),"")) -> 27 | H66: 2 contacts | I66: AcademicTransfer | K66: Benigno | L66: Reis | O66: =_xlfn.TEXTJOIN(", ",TRUE(),K66:N66) -> Benigno, Reis | P66: Referee action needed
A67: Northwestern University, Department of Economics | B67: Assistant Professor (any field) | C67: Evanston, US | D67: Academic · Macro / economics | E67: 46341 | F67: 46341 | G67: =IF(F67<>"",F67-TODAY(),IF(E67<>"",E67-TODAY(),"")) -> 27 | H67: 3 | I67: EconJobMarket (ad 12570) | K67: Benigno | L67: Reis | M67: Hofmann | O67: =_xlfn.TEXTJOIN(", ",TRUE(),K67:N67) -> Benigno, Reis, Hofmann | P67: On platform – check attached
A68: Princeton University, Department of Economics | B68: Assistant Professor (any field) | C68: Princeton, US | D68: Academic · Macro / economics | E68: 46341 | F68: 46341 | G68: =IF(F68<>"",F68-TODAY(),IF(E68<>"",E68-TODAY(),"")) -> 27 | H68: 3 | I68: Interfolio 191051 | J68: JOE says 15 Nov; EJM 12577 says 1 Dec with review from 15 Nov — use 15 Nov | K68: Benigno | L68: Reis | M68: Hofmann | O68: =_xlfn.TEXTJOIN(", ",TRUE(),K68:N68) -> Benigno, Reis, Hofmann | P68: On platform – check attached
A69: University of Wisconsin–Madison | B69: Assistant Professor of Economics (broad, incl. macro and international) | C69: Madison, US | D69: Academic · Macro / economics | E69: 46341 | F69: 46341 | G69: =IF(F69<>"",F69-TODAY(),IF(E69<>"",E69-TODAY(),"")) -> 27 | H69: 3 | I69: jobs.wisc.edu JR10014688 / EconJobMarket (ad 12637) | K69: Benigno | L69: Reis | M69: Hofmann | O69: =_xlfn.TEXTJOIN(", ",TRUE(),K69:N69) -> Benigno, Reis, Hofmann | P69: On platform – check attached
A70: University of Texas at Austin, Department of Economics | B70: Assistant Professor (one slot macro/international) | C70: Austin, US | D70: Academic · Macro / economics | E70: 46341 | F70: 46341 | G70: =IF(F70<>"",F70-TODAY(),IF(E70<>"",E70-TODAY(),"")) -> 27 | H70: 3 | I70: AEA JOE | K70: Benigno | L70: Reis | M70: Hofmann | O70: =_xlfn.TEXTJOIN(", ",TRUE(),K70:N70) -> Benigno, Reis, Hofmann | P70: On platform – check attached
A71: Johns Hopkins University | B71: Assistant Professor (open field) | C71: Baltimore, US | D71: Academic · Macro / economics | E71: 46341 | F71: 46341 | G71: =IF(F71<>"",F71-TODAY(),IF(E71<>"",E71-TODAY(),"")) -> 27 | H71: 3 | I71: Interfolio 193762 | J71: Priority 15 Nov; final 31 Dec | K71: Benigno | L71: Reis | M71: Hofmann | O71: =_xlfn.TEXTJOIN(", ",TRUE(),K71:N71) -> Benigno, Reis, Hofmann | P71: On platform – check attached
A72: Rice University | B72: Open rank, Labor and Public Economics | C72: Houston, US | D72: Academic · Macro / economics | E72: 46341 | F72: 46341 | G72: =IF(F72<>"",F72-TODAY(),IF(E72<>"",E72-TODAY(),"")) -> 27 | H72: Not stated – check ad | I72: Interfolio 192587 / EconJobMarket (ad 12638) | J72: Full consideration 15 Nov | K72: Benigno | L72: Reis | M72: Hofmann | O72: =_xlfn.TEXTJOIN(", ",TRUE(),K72:N72) -> Benigno, Reis, Hofmann | P72: On platform – check attached
A73: Duke Fuqua | B73: Tenure-track faculty, Finance | C73: Durham, US | D73: Academic · Finance | E73: 46341 | F73: 46341 | G73: =IF(F73<>"",F73-TODAY(),IF(E73<>"",E73-TODAY(),"")) -> 27 | H73: 3 | I73: AcademicJobsOnline 32259 | K73: Benigno | L73: Reis | M73: Chaudhary | O73: =_xlfn.TEXTJOIN(", ",TRUE(),K73:N73) -> Benigno, Reis, Chaudhary | P73: On platform – check attached
A74: George Washington University – School of Business | B74: Assistant Professor of Finance | C74: Washington DC, US | D74: Academic · Finance | E74: 46341 | F74: 46341 | G74: =IF(F74<>"",F74-TODAY(),IF(E74<>"",E74-TODAY(),"")) -> 27 | H74: 3 | I74: University portal (posting 127887) – letters emailed to finance.dept@gwu.edu | K74: Benigno | L74: Reis | M74: Chaudhary | O74: =_xlfn.TEXTJOIN(", ",TRUE(),K74:N74) -> Benigno, Reis, Chaudhary | P74: Referee action needed
A75: Banco de España, Research | B75: Research Economist (2026–27 PhD job market) | C75: Madrid, ES | D75: Policy | E75: 46342 | F75: 46342 | G75: =IF(F75<>"",F75-TODAY(),IF(E75<>"",E75-TODAY(),"")) -> 28 | H75: At least 3 | I75: EconJobMarket (ad 12796) | J75: econjobmarket.org/positions/12796 – midnight UTC | K75: Benigno | L75: Reis | M75: Hofmann | O75: =_xlfn.TEXTJOIN(", ",TRUE(),K75:N75) -> Benigno, Reis, Hofmann | P75: On platform – check attached
A76: Copenhagen Business School, Finance | B76: Assistant Professor of Finance | C76: Copenhagen, DK | D76: Academic · Finance | E76: 46335 | F76: 46342 | G76: =IF(F76<>"",F76-TODAY(),IF(E76<>"",E76-TODAY(),"")) -> 28 | H76: Not stated – check ad | I76: CBS HR portal | J76: Full consideration 9 Nov; final 16 Nov 23:59 UTC | K76: Benigno | L76: Reis | M76: Chaudhary | O76: =_xlfn.TEXTJOIN(", ",TRUE(),K76:N76) -> Benigno, Reis, Chaudhary | P76: Referee action needed
A77: University of British Columbia, VSE | B77: Assistant Professor (macro / international macro) | C77: Vancouver, CA | D77: Academic · Macro / economics | E77: 46342 | F77: 46342 | G77: =IF(F77<>"",F77-TODAY(),IF(E77<>"",E77-TODAY(),"")) -> 28 | H77: At least 3 – submitted directly by referees via EJM | I77: EconJobMarket (ad 12839) | J77: econjobmarket.org/positions/12839 | K77: Benigno | L77: Reis | M77: Hofmann | O77: =_xlfn.TEXTJOIN(", ",TRUE(),K77:N77) -> Benigno, Reis, Hofmann | P77: On platform – check attached
A78: University of Rochester | B78: Assistant Professor (macro / international macro) | C78: Rochester, US | D78: Academic · Macro / economics | E78: 46342 | F78: 46342 | G78: =IF(F78<>"",F78-TODAY(),IF(E78<>"",E78-TODAY(),"")) -> 28 | H78: 3 | I78: Interfolio 192002 | K78: Benigno | L78: Reis | M78: Hofmann | O78: =_xlfn.TEXTJOIN(", ",TRUE(),K78:N78) -> Benigno, Reis, Hofmann | P78: On platform – check attached
A79: Washington University in St. Louis | B79: Assistant/Associate/Full Professor (macro emphasised) | C79: St. Louis, US | D79: Academic · Macro / economics | E79: 46342 | F79: 46342 | G79: =IF(F79<>"",F79-TODAY(),IF(E79<>"",E79-TODAY(),"")) -> 28 | H79: 3 | I79: EconJobMarket (ad 12678) | J79: Rolling review | K79: Benigno | L79: Reis | M79: Hofmann | O79: =_xlfn.TEXTJOIN(", ",TRUE(),K79:N79) -> Benigno, Reis, Hofmann | P79: On platform – check attached
A80: WU Vienna | B80: Assistant Professor of Finance – CONDITIONAL | C80: Vienna, AT | D80: Academic · Finance | E80: 46342 | F80: 46342 | G80: =IF(F80<>"",F80-TODAY(),IF(E80<>"",E80-TODAY(),"")) -> 28 | H80: Not stated – check ad | I80: WU portal | K80: Benigno | L80: Reis | M80: Chaudhary | O80: =_xlfn.TEXTJOIN(", ",TRUE(),K80:N80) -> Benigno, Reis, Chaudhary | P80: Referee action needed
A81: Stockholm School of Economics | B81: Two tenure-track positions in Economics | C81: Stockholm, SE | D81: Academic · Macro / economics | E81: 46342 | F81: 46342 | G81: =IF(F81<>"",F81-TODAY(),IF(E81<>"",E81-TODAY(),"")) -> 28 | H81: 3 | I81: EconJobMarket (ad 12714) | K81: Benigno | L81: Reis | M81: Hofmann | O81: =_xlfn.TEXTJOIN(", ",TRUE(),K81:N81) -> Benigno, Reis, Hofmann | P81: On platform – check attached
A82: Université libre de Bruxelles (Solvay / DULBEA) | B82: Policy-relevant applied micro (labour, public finance) – Asst/Assoc | C82: Brussels, BE | D82: Academic · Macro / economics | E82: 46342 | F82: 46342 | G82: =IF(F82<>"",F82-TODAY(),IF(E82<>"",E82-TODAY(),"")) -> 28 | H82: 5 | I82: EconJobMarket (ad 12624) | J82: Five referee contacts | K82: Benigno | L82: Reis | M82: Hofmann | N82: Chaudhary | O82: =_xlfn.TEXTJOIN(", ",TRUE(),K82:N82) -> Benigno, Reis, Hofmann, Chaudhary | P82: On platform – check attached
A83: Columbia Business School, Finance | B83: Assistant/Associate Professor – Finance | C83: New York, US | D83: Academic · Finance | E83: 46343 | F83: 46343 | G83: =IF(F83<>"",F83-TODAY(),IF(E83<>"",E83-TODAY(),"")) -> 29 | H83: Not stated – check ad | I83: Interfolio 194179 | K83: Benigno | L83: Reis | M83: Chaudhary | O83: =_xlfn.TEXTJOIN(", ",TRUE(),K83:N83) -> Benigno, Reis, Chaudhary | P83: On platform – check attached
A84: Amsterdam Business School | B84: Assistant Professor | C84: Amsterdam, NL | D84: Academic · Finance | E84: 46343 | F84: 46343 | G84: =IF(F84<>"",F84-TODAY(),IF(E84<>"",E84-TODAY(),"")) -> 29 | H84: 3 | I84: EconJobMarket | K84: Benigno | L84: Reis | M84: Chaudhary | O84: =_xlfn.TEXTJOIN(", ",TRUE(),K84:N84) -> Benigno, Reis, Chaudhary | P84: On platform – check attached
A85: Columbia Business School – Economics Division | B85: Assistant/Associate Professor (macro among areas) | C85: New York, US | D85: Academic · Macro / economics | E85: 46343 | F85: 46343 | G85: =IF(F85<>"",F85-TODAY(),IF(E85<>"",E85-TODAY(),"")) -> 29 | H85: Not stated – check ad | I85: Interfolio 194182 | K85: Benigno | L85: Reis | M85: Hofmann | O85: =_xlfn.TEXTJOIN(", ",TRUE(),K85:N85) -> Benigno, Reis, Hofmann | P85: On platform – check attached
A86: Hoover Institution | B86: Hoover Fellow (1–3 years, early career, policy) | C86: Stanford, US | D86: Fellowship · Macro / economics | E86: 46343 | F86: 46343 | G86: =IF(F86<>"",F86-TODAY(),IF(E86<>"",E86-TODAY(),"")) -> 29 | H86: Not stated – check ad | I86: Hoover portal | K86: Benigno | L86: Reis | M86: Hofmann | O86: =_xlfn.TEXTJOIN(", ",TRUE(),K86:N86) -> Benigno, Reis, Hofmann | P86: Referee action needed
A87: UQAM, Département des sciences économiques | B87: Professor, International Economics | C87: Montréal, CA | D87: Academic · Macro / economics | E87: 46344 | F87: 46344 | G87: =IF(F87<>"",F87-TODAY(),IF(E87<>"",E87-TODAY(),"")) -> 30 | H87: 3 | I87: EconJobMarket (ad 12695) | K87: Benigno | L87: Reis | M87: Hofmann | O87: =_xlfn.TEXTJOIN(", ",TRUE(),K87:N87) -> Benigno, Reis, Hofmann | P87: On platform – check attached
A88: Erasmus School of Economics | B88: Assistant Professor in Finance (TT) | C88: Rotterdam, NL | D88: Academic · Finance | E88: 46344 | F88: 46344 | G88: =IF(F88<>"",F88-TODAY(),IF(E88<>"",E88-TODAY(),"")) -> 30 | H88: 3 | I88: EconJobMarket (ad 12833) | K88: Benigno | L88: Reis | M88: Chaudhary | O88: =_xlfn.TEXTJOIN(", ",TRUE(),K88:N88) -> Benigno, Reis, Chaudhary | P88: On platform – check attached
A89: Federal Reserve Bank of San Francisco | B89: Economist / Senior Economist | C89: San Francisco, US | D89: Policy | E89: 46344 | F89: 46344 | G89: =IF(F89<>"",F89-TODAY(),IF(E89<>"",E89-TODAY(),"")) -> 30 | H89: Not stated – check ad | I89: EconJobMarket (ad 12609) | K89: Benigno | L89: Reis | M89: Hofmann | O89: =_xlfn.TEXTJOIN(", ",TRUE(),K89:N89) -> Benigno, Reis, Hofmann | P89: On platform – check attached
A90: UC Berkeley Haas | B90: Assistant Professor, Finance | C90: Berkeley, US | D90: Academic · Finance | E90: 46344 | F90: 46344 | G90: =IF(F90<>"",F90-TODAY(),IF(E90<>"",E90-TODAY(),"")) -> 30 | H90: 3 | I90: EconJobMarket (ad 12556) | K90: Benigno | L90: Reis | M90: Chaudhary | O90: =_xlfn.TEXTJOIN(", ",TRUE(),K90:N90) -> Benigno, Reis, Chaudhary | P90: On platform – check attached
A91: ifo Institute – Center for International Economics | B91: Postdoctoral Researcher (international trade) | C91: Munich, DE | D91: Research institute · Macro / economics | E91: 46344 | F91: 46344 | G91: =IF(F91<>"",F91-TODAY(),IF(E91<>"",E91-TODAY(),"")) -> 30 | H91: 3 | I91: EconJobMarket (ad 12844) | J91: Interviews at EEA job market 14–17 Dec | K91: Benigno | L91: Reis | M91: Hofmann | O91: =_xlfn.TEXTJOIN(", ",TRUE(),K91:N91) -> Benigno, Reis, Hofmann | P91: On platform – check attached
A92: UC Berkeley Haas | B92: Assistant Professor, Economic Analysis & Policy | C92: Berkeley, US | D92: Academic · Macro / economics | E92: 46344 | F92: 46344 | G92: =IF(F92<>"",F92-TODAY(),IF(E92<>"",E92-TODAY(),"")) -> 30 | H92: 3 | I92: EconJobMarket (ad 12616) | K92: Benigno | L92: Reis | M92: Hofmann | O92: =_xlfn.TEXTJOIN(", ",TRUE(),K92:N92) -> Benigno, Reis, Hofmann | P92: On platform – check attached
A93: NYU Stern, Finance | B93: Assistant Professor of Finance | C93: New York, US | D93: Academic · Finance | E93: 46339 | F93: 46346 | G93: =IF(F93<>"",F93-TODAY(),IF(E93<>"",E93-TODAY(),"")) -> 32 | H93: Not stated – check ad | I93: Interfolio 194815 | J93: Full consideration 13 Nov; final 20 Nov | K93: Benigno | L93: Reis | M93: Chaudhary | O93: =_xlfn.TEXTJOIN(", ",TRUE(),K93:N93) -> Benigno, Reis, Chaudhary | P93: On platform – check attached
A94: HEC Montréal, Finance | B94: Tenure-track, open rank | C94: Montréal, CA | D94: Academic · Finance | E94: 46346 | F94: 46346 | G94: =IF(F94<>"",F94-TODAY(),IF(E94<>"",E94-TODAY(),"")) -> 32 | H94: Up to 3 | I94: Qualtrics form | J94: hecmontreal.eu.qualtrics.com/jfe/form/SV_bvHfE0IBLXmB0H4 | K94: Benigno | L94: Reis | M94: Chaudhary | O94: =_xlfn.TEXTJOIN(", ",TRUE(),K94:N94) -> Benigno, Reis, Chaudhary | P94: Referee action needed
A95: ESSEC Business School, Finance | B95: Assistant Professor of Finance (asset pricing or real-estate finance) | C95: Cergy, FR | D95: Academic · Finance | E95: 46346 | F95: 46346 | G95: =IF(F95<>"",F95-TODAY(),IF(E95<>"",E95-TODAY(),"")) -> 32 | H95: 3 | I95: EconJobMarket (ad 12777) | K95: Benigno | L95: Reis | M95: Chaudhary | O95: =_xlfn.TEXTJOIN(", ",TRUE(),K95:N95) -> Benigno, Reis, Chaudhary | P95: On platform – check attached
A96: Wharton, Finance | B96: Assistant Professor of Finance | C96: Philadelphia, US | D96: Academic · Finance | E96: 46346 | F96: 46346 | G96: =IF(F96<>"",F96-TODAY(),IF(E96<>"",E96-TODAY(),"")) -> 32 | H96: 3 (+ optional 4th) | I96: AcademicJobsOnline 32965 | J96: Full consideration 20 Nov | K96: Benigno | L96: Reis | M96: Chaudhary | O96: =_xlfn.TEXTJOIN(", ",TRUE(),K96:N96) -> Benigno, Reis, Chaudhary | P96: On platform – check attached
A97: Bank of Canada | B97: PhD Researcher (2026–27 PhD job market) | C97: Ottawa, CA | D97: Policy | E97: 46507 | F97: 46346 | G97: =IF(F97<>"",F97-TODAY(),IF(E97<>"",E97-TODAY(),"")) -> 32 | H97: 3 | I97: EconJobMarket | J97: Recommended by 20 Nov (virtual interviews from 1 Dec); final 30 Apr 2027 | K97: Benigno | L97: Reis | M97: Hofmann | O97: =_xlfn.TEXTJOIN(", ",TRUE(),K97:N97) -> Benigno, Reis, Hofmann | P97: On platform – check attached
A98: Nova SBE | B98: Finance Professor (tenure track) | C98: Carcavelos, PT | D98: Academic · Finance | E98: 46346 | F98: 46346 | G98: =IF(F98<>"",F98-TODAY(),IF(E98<>"",E98-TODAY(),"")) -> 32 | H98: 3 | I98: EconJobMarket (ad 12829) | K98: Benigno | L98: Reis | M98: Chaudhary | O98: =_xlfn.TEXTJOIN(", ",TRUE(),K98:N98) -> Benigno, Reis, Chaudhary | P98: On platform – check attached
A99: University College Dublin | B99: Lecturer / Assistant Professor in Economics (5-year, any field) | C99: Dublin, IE | D99: Academic · Macro / economics | E99: 46346 | F99: 46346 | G99: =IF(F99<>"",F99-TODAY(),IF(E99<>"",E99-TODAY(),"")) -> 32 | H99: Not stated – check ad | I99: UCD portal (ref 020071) / EconJobMarket (ad 12694) | J99: 12:00 noon Irish time | K99: Benigno | L99: Reis | M99: Hofmann | O99: =_xlfn.TEXTJOIN(", ",TRUE(),K99:N99) -> Benigno, Reis, Hofmann | P99: On platform – check attached
A100: University of Bonn | B100: Assistant Professor (W1→W2) in Finance | C100: Bonn, DE | D100: Academic · Finance | E100: 46346 | F100: 46346 | G100: =IF(F100<>"",F100-TODAY(),IF(E100<>"",E100-TODAY(),"")) -> 32 | H100: 3 | I100: EconJobMarket (ad 12594) | J100: Full-consideration date | K100: Benigno | L100: Reis | M100: Chaudhary | O100: =_xlfn.TEXTJOIN(", ",TRUE(),K100:N100) -> Benigno, Reis, Chaudhary | P100: On platform – check attached
A101: Texas A&M – Mays Business School | B101: TT Assistant Professor of Finance (incl. macro-finance, banking) | C101: College Station, US | D101: Academic · Finance | E101: 46346 | F101: 46346 | G101: =IF(F101<>"",F101-TODAY(),IF(E101<>"",E101-TODAY(),"")) -> 32 | H101: Not stated – check ad | I101: Interfolio 188161 | K101: Benigno | L101: Reis | M101: Chaudhary | O101: =_xlfn.TEXTJOIN(", ",TRUE(),K101:N101) -> Benigno, Reis, Chaudhary | P101: On platform – check attached
...

Sheet By referee
A1: Letters per referee — live counts from the Applications sheet
A2: Counts update automatically when referee assignments or statuses change on the first sheet. A platform letter (EJM, JOE, Interfolio, AJO) is written once and reused, so the real workload is the number of distinct platforms plus the direct-email items.
A4: Referee | B4: Applications naming this referee | C4: Earliest letters due | D4: Due by 31 Oct | E4: Due 1–8 Nov | F4: Due 9–16 Nov | G4: Due 17–30 Nov | H4: Due Dec 2026 | I4: Due 2027 | J4: Via EJM / JOE (one upload) | K4: Via Interfolio / AJO | L4: Other (own portal, direct email, names only) | M4: Needs the referee to act separately
A5: Benigno | B5: =COUNTIF(Applications!$K$5:$K$145,"*Benigno*") -> 141 | C5: =IF(COUNTIFS(Applications!$O$5:$O$145,"*Benigno*",Applications!$F$5:$F$145,">="&TODAY())=0,"",_xlfn.MINIFS(Applications!$F$5:$F$145,Applications!$O$5:$O$145,"*Reis*",Applications!$F$5:$F$145,">="&TODAY())) -> 46325 | D5: =COUNTIFS(Applications!$O$5:$O$145,"*Benigno*",Applications!$F$5:$F$145,"<="&DATE(2026,10,31)) -> 2 | E5: =COUNTIFS(Applications!$O$5:$O$145,"*Benigno*",Applications!$F$5:$F$145,">="&DATE(2026,11,1),Applications!$F$5:$F$145,"<="&DATE(2026,11,8)) -> 14 | F5: =COUNTIFS(Applications!$O$5:$O$145,"*Benigno*",Applications!$F$5:$F$145,">="&DATE(2026,11,9),Applications!$F$5:$F$145,"<="&DATE(2026,11,16)) -> 56 | G5: =COUNTIFS(Applications!$O$5:$O$145,"*Benigno*",Applications!$F$5:$F$145,">="&DATE(2026,11,17),Applications!$F$5:$F$145,"<="&DATE(2026,11,30)) -> 37 | H5: =COUNTIFS(Applications!$O$5:$O$145,"*Benigno*",Applications!$F$5:$F$145,">="&DATE(2026,12,1),Applications!$F$5:$F$145,"<="&DATE(2026,12,31)) -> 17 | I5: =COUNTIFS(Applications!$O$5:$O$145,"*Benigno*",Applications!$F$5:$F$145,">="&DATE(2027,1,1)) -> 6 | J5: =COUNTIFS(Applications!$O$5:$O$145,"*Benigno*",Applications!$I$5:$I$145,"*EconJobMarket*")+COUNTIFS(Applications!$O$5:$O$145,"*Benigno*",Applications!$I$5:$I$145,"*JOE*") -> 85 | K5: =COUNTIFS(Applications!$O$5:$O$145,"*Benigno*",Applications!$I$5:$I$145,"*Interfolio*")+COUNTIFS(Applications!$O$5:$O$145,"*Benigno*",Applications!$I$5:$I$145,"*AcademicJobsOnline*") -> 24 | L5: =B5-J5-K5 -> 32 | M5: =COUNTIFS(Applications!$O$5:$O$145,"*Benigno*",Applications!$P$5:$P$145,"Referee action needed") -> 28
A6: Reis | B6: =COUNTIF(Applications!$O$5:$O$145,"*Reis*") -> 139 | C6: =IF(COUNTIFS(Applications!$O$5:$O$145,"*Reis*",Applications!$F$5:$F$145,">="&TODAY())=0,"",_xlfn.MINIFS(Applications!$F$5:$F$145,Applications!$O$5:$O$145,"*Reis*",Applications!$F$5:$F$145,">="&TODAY())) -> 46325 | D6: =COUNTIFS(Applications!$O$5:$O$145,"*Reis*",Applications!$F$5:$F$145,"<="&DATE(2026,10,31)) -> 2 | E6: =COUNTIFS(Applications!$O$5:$O$145,"*Reis*",Applications!$F$5:$F$145,">="&DATE(2026,11,1),Applications!$F$5:$F$145,"<="&DATE(2026,11,8)) -> 14 | F6: =COUNTIFS(Applications!$O$5:$O$145,"*Reis*",Applications!$F$5:$F$145,">="&DATE(2026,11,9),Applications!$F$5:$F$145,"<="&DATE(2026,11,16)) -> 56 | G6: =COUNTIFS(Applications!$O$5:$O$145,"*Reis*",Applications!$F$5:$F$145,">="&DATE(2026,11,17),Applications!$F$5:$F$145,"<="&DATE(2026,11,30)) -> 37 | H6: =COUNTIFS(Applications!$O$5:$O$145,"*Reis*",Applications!$F$5:$F$145,">="&DATE(2026,12,1),Applications!$F$5:$F$145,"<="&DATE(2026,12,31)) -> 15 | I6: =COUNTIFS(Applications!$O$5:$O$145,"*Reis*",Applications!$F$5:$F$145,">="&DATE(2027,1,1)) -> 6 | J6: =COUNTIFS(Applications!$O$5:$O$145,"*Reis*",Applications!$I$5:$I$145,"*EconJobMarket*")+COUNTIFS(Applications!$O$5:$O$145,"*Reis*",Applications!$I$5:$I$145,"*JOE*") -> 85 | K6: =COUNTIFS(Applications!$O$5:$O$145,"*Reis*",Applications!$I$5:$I$145,"*Interfolio*")+COUNTIFS(Applications!$O$5:$O$145,"*Reis*",Applications!$I$5:$I$145,"*AcademicJobsOnline*") -> 24 | L6: =B6-J6-K6 -> 30 | M6: =COUNTIFS(Applications!$O$5:$O$145,"*Reis*",Applications!$P$5:$P$145,"Referee action needed") -> 26
A7: Hofmann | B7: =COUNTIF(Applications!$O$5:$O$145,"*Hofmann*") -> 88 | C7: =IF(COUNTIFS(Applications!$O$5:$O$145,"*Hofmann*",Applications!$F$5:$F$145,">="&TODAY())=0,"",_xlfn.MINIFS(Applications!$F$5:$F$145,Applications!$O$5:$O$145,"*Hofmann*",Applications!$F$5:$F$145,">="&TODAY())) -> 46327 | D7: =COUNTIFS(Applications!$O$5:$O$145,"*Hofmann*",Applications!$F$5:$F$145,"<="&DATE(2026,10,31)) -> 0 | E7: =COUNTIFS(Applications!$O$5:$O$145,"*Hofmann*",Applications!$F$5:$F$145,">="&DATE(2026,11,1),Applications!$F$5:$F$145,"<="&DATE(2026,11,8)) -> 12 | F7: =COUNTIFS(Applications!$O$5:$O$145,"*Hofmann*",Applications!$F$5:$F$145,">="&DATE(2026,11,9),Applications!$F$5:$F$145,"<="&DATE(2026,11,16)) -> 39 | G7: =COUNTIFS(Applications!$O$5:$O$145,"*Hofmann*",Applications!$F$5:$F$145,">="&DATE(2026,11,17),Applications!$F$5:$F$145,"<="&DATE(2026,11,30)) -> 19 | H7: =COUNTIFS(Applications!$O$5:$O$145,"*Hofmann*",Applications!$F$5:$F$145,">="&DATE(2026,12,1),Applications!$F$5:$F$145,"<="&DATE(2026,12,31)) -> 12 | I7: =COUNTIFS(Applications!$O$5:$O$145,"*Hofmann*",Applications!$F$5:$F$145,">="&DATE(2027,1,1)) -> 4 | J7: =COUNTIFS(Applications!$O$5:$O$145,"*Hofmann*",Applications!$I$5:$I$145,"*EconJobMarket*")+COUNTIFS(Applications!$O$5:$O$145,"*Hofmann*",Applications!$I$5:$I$145,"*JOE*") -> 65 | K7: =COUNTIFS(Applications!$O$5:$O$145,"*Hofmann*",Applications!$I$5:$I$145,"*Interfolio*")+COUNTIFS(Applications!$O$5:$O$145,"*Hofmann*",Applications!$I$5:$I$145,"*AcademicJobsOnline*") -> 14 | L7: =B7-J7-K7 -> 9 | M7: =COUNTIFS(Applications!$O$5:$O$145,"*Hofmann*",Applications!$P$5:$P$145,"Referee action needed") -> 10
A8: Chaudhary | B8: =COUNTIF(Applications!$O$5:$O$145,"*Chaudhary*") -> 38 | C8: =IF(COUNTIFS(Applications!$O$5:$O$145,"*Chaudhary*",Applications!$F$5:$F$145,">="&TODAY())=0,"",_xlfn.MINIFS(Applications!$F$5:$F$145,Applications!$O$5:$O$145,"*Chaudhary*",Applications!$F$5:$F$145,">="&TODAY())) -> 46327 | D8: =COUNTIFS(Applications!$O$5:$O$145,"*Chaudhary*",Applications!$F$5:$F$145,"<="&DATE(2026,10,31)) -> 0 | E8: =COUNTIFS(Applications!$O$5:$O$145,"*Chaudhary*",Applications!$F$5:$F$145,">="&DATE(2026,11,1),Applications!$F$5:$F$145,"<="&DATE(2026,11,8)) -> 1 | F8: =COUNTIFS(Applications!$O$5:$O$145,"*Chaudhary*",Applications!$F$5:$F$145,">="&DATE(2026,11,9),Applications!$F$5:$F$145,"<="&DATE(2026,11,16)) -> 15 | G8: =COUNTIFS(Applications!$O$5:$O$145,"*Chaudhary*",Applications!$F$5:$F$145,">="&DATE(2026,11,17),Applications!$F$5:$F$145,"<="&DATE(2026,11,30)) -> 15 | H8: =COUNTIFS(Applications!$O$5:$O$145,"*Chaudhary*",Applications!$F$5:$F$145,">="&DATE(2026,12,1),Applications!$F$5:$F$145,"<="&DATE(2026,12,31)) -> 1 | I8: =COUNTIFS(Applications!$O$5:$O$145,"*Chaudhary*",Applications!$F$5:$F$145,">="&DATE(2027,1,1)) -> 2 | J8: =COUNTIFS(Applications!$O$5:$O$145,"*Chaudhary*",Applications!$I$5:$I$145,"*EconJobMarket*")+COUNTIFS(Applications!$O$5:$O$145,"*Chaudhary*",Applications!$I$5:$I$145,"*JOE*") -> 15 | K8: =COUNTIFS(Applications!$O$5:$O$145,"*Chaudhary*",Applications!$I$5:$I$145,"*Interfolio*")+COUNTIFS(Applications!$O$5:$O$145,"*Chaudhary*",Applications!$I$5:$I$145,"*AcademicJobsOnline*") -> 8 | L8: =B8-J8-K8 -> 15 | M8: =COUNTIFS(Applications!$O$5:$O$145,"*Chaudhary*",Applications!$P$5:$P$145,"Referee action needed") -> 11
